treesitter_highlighter-1.1.1.dist-info/METADATA
treesitter_highlighter-1.1.1.dist-info/RECORD
treesitter_highlighter-1.1.1.dist-info/WHEEL
treesitter_highlighter.so