Metadata-Version: 2.1
Name: treesitter_highlighter
Version: 1.1.1
Summary: Highlighter library
